searcheval/__init__.py
searcheval/helpers.py
searcheval/metrics.py
searcheval/test/__init__.py
searcheval/test/test_metrics.py
searcheval-0.2.2.dist-info/LICENSE.txt
searcheval-0.2.2.dist-info/METADATA
searcheval-0.2.2.dist-info/WHEEL
searcheval-0.2.2.dist-info/top_level.txt
searcheval-0.2.2.dist-info/RECORD
